btcpay/__init__.py
btcpay/client.py
btcpay/crypto.py
btcpay-1.0.3.dist-info/DESCRIPTION.rst
btcpay-1.0.3.dist-info/METADATA
btcpay-1.0.3.dist-info/RECORD
btcpay-1.0.3.dist-info/WHEEL
btcpay-1.0.3.dist-info/metadata.json
btcpay-1.0.3.dist-info/top_level.txt
