Metadata-Version: 2.0
Name: btcpay
Version: 1.0.3
Summary: Accept bitcoin with BTCPay
Home-page: https://github.com/joeblackwaslike/btcpay-python
Author: Joe Black
Author-email: me@joeblack.nyc
License: MIT
Download-URL: https://github.com/joeblackwaslike/btcpay-python/tarball/v1.0.3
Keywords: bitcoin,payments,crypto
Platform: UNKNOWN
Classifier: Programming Language :: Python :: 3.6
Classifier: Programming Language :: Python :: 3 :: Only
Classifier: Development Status :: 5 - Production/Stable
Classifier: Environment :: Web Environment
Classifier: Intended Audience :: Developers
Classifier: License :: OSI Approved :: MIT License
Classifier: Operating System :: OS Independent
Classifier: Topic :: Software Development :: Libraries :: Python Modules
Classifier: Topic :: Office/Business :: Financial
Requires-Dist: ecdsa
Requires-Dist: requests
